Workbook

Sheet Visual Summary 

Sheet Dashboard
B3: Monthly Revenue Summary
B4: Month | C4: Budgeted Revenue | D4: Actual Revenue | E4: Revenue Variance | F4: Volume Variance | G4: Price Variance | H4: Var %
B5: 45383 | C5: =SUMIF('Derived Data'!$A$6:$N$53,Dashboard!B5,'Derived Data'!$K$6:$K$53) -> 16900000 | D5: =SUMIF('Derived Data'!$A$6:$N$53,Dashboard!B5,'Derived Data'!$L$6:$L$53) -> 16937420 | E5: =D5-C5 -> 37420 | F5: =SUMIF('Derived Data'!$A$6:$N$53,Dashboard!B5,'Derived Data'!$M$6:$M$53) -> 21000 | G5: =SUMIF('Derived Data'!$A$6:$N$53,Dashboard!B5,'Derived Data'!$N$6:$N$53) -> 16420 | H5: =IFERROR(E5/C5,"n/a") -> 0.0022142012
B6: =EDATE(B5,1) -> 45413 | C6: =SUMIF('Derived Data'!$A$6:$N$53,Dashboard!B6,'Derived Data'!$K$6:$K$53) -> 16970000 | D6: =SUMIF('Derived Data'!$A$6:$N$53,Dashboard!B6,'Derived Data'!$L$6:$L$53) -> 16861025 | E6: =D6-C6 -> -108975 | F6: =SUMIF('Derived Data'!$A$6:$N$534,Dashboard!B6,'Derived Data'!$M$6:$M$53) -> 7500 | G6: =SUMIF('Derived Data'!$A$6:$N$53,Dashboard!B6,'Derived Data'!$N$6:$N$53) -> -116475 | H6: =IFERROR(E6/C6,"n/a") -> -0.0064216264
B7: =EDATE(B6,1) -> 45444 | C7: =SUMIF('Derived Data'!$A$6:$N$53,Dashboard!B7,'Derived Data'!$K$6:$K$53) -> 17010000 | D7: =SUMIF('Derived Data'!$A$6:$N$53,Dashboard!B7,'Derived Data'!$L$6:$L$53) -> 17098575 | E7: =D7-C7 -> 88575 | F7: =SUMIF('Derived Data'!$A$6:$N$534,Dashboard!B7,'Derived Data'!$M$6:$M$53) -> -12500 | G7: =SUMIF('Derived Data'!$A$6:$N$53,Dashboard!B7,'Derived Data'!$N$6:$N$53) -> 101075 | H7: =IFERROR(E7/C7,"n/a") -> 0.005207231
B8: =EDATE(B7,1) -> 45474 | C8: =SUMIF('Derived Data'!$A$6:$N$53,Dashboard!B8,'Derived Data'!$K$6:$K$53) -> 16900000 | D8: =SUMIF('Derived Data'!$A$6:$N$53,Dashboard!B8,'Derived Data'!$L$6:$L$53) -> 16835000 | E8: =D8-C8 -> -65000 | F8: =SUMIF('Derived Data'!$A$6:$N$534,Dashboard!B8,'Derived Data'!$M$6:$M$53) -> -45000 | G8: =SUMIF('Derived Data'!$A$6:$N$53,Dashboard!B8,'Derived Data'!$N$6:$N$53) -> -20000 | H8: =IFERROR(E8/C8,"n/a") -> -0.0038461538
B9: =EDATE(B8,1) -> 45505 | C9: =SUMIF('Derived Data'!$A$6:$N$53,Dashboard!B9,'Derived Data'!$K$6:$K$53) -> 16840000 | D9: =SUMIF('Derived Data'!$A$6:$N$53,Dashboard!B9,'Derived Data'!$L$6:$L$53) -> 16925350 | E9: =D9-C9 -> 85350 | F9: =SUMIF('Derived Data'!$A$6:$N$534,Dashboard!B9,'Derived Data'!$M$6:$M$53) -> 112500 | G9: =SUMIF('Derived Data'!$A$6:$N$53,Dashboard!B9,'Derived Data'!$N$6:$N$53) -> -27150 | H9: =IFERROR(E9/C9,"n/a") -> 0.0050682898
B10: =EDATE(B9,1) -> 45536 | C10: =SUMIF('Derived Data'!$A$6:$N$53,Dashboard!B10,'Derived Data'!$K$6:$K$53) -> 17020000 | D10: =SUMIF('Derived Data'!$A$6:$N$53,Dashboard!B10,'Derived Data'!$L$6:$L$53) -> 17214375 | E10: =D10-C10 -> 194375 | F10: =SUMIF('Derived Data'!$A$6:$N$534,Dashboard!B10,'Derived Data'!$M$6:$M$53) -> 160000 | G10: =SUMIF('Derived Data'!$A$6:$N$53,Dashboard!B10,'Derived Data'!$N$6:$N$53) -> 34375 | H10: =IFERROR(E10/C10,"n/a") -> 0.011420388
B11: =EDATE(B10,1) -> 45566 | C11: =SUMIF('Derived Data'!$A$6:$N$53,Dashboard!B11,'Derived Data'!$K$6:$K$53) -> 17825000 | D11: =SUMIF('Derived Data'!$A$6:$N$53,Dashboard!B11,'Derived Data'!$L$6:$L$53) -> 18098575 | E11: =D11-C11 -> 273575 | F11: =SUMIF('Derived Data'!$A$6:$N$534,Dashboard!B11,'Derived Data'!$M$6:$M$53) -> 500000 | G11: =SUMIF('Derived Data'!$A$6:$N$53,Dashboard!B11,'Derived Data'!$N$6:$N$53) -> -226425 | H11: =IFERROR(E11/C11,"n/a") -> 0.015347826
B12: =EDATE(B11,1) -> 45597 | C12: =SUMIF('Derived Data'!$A$6:$N$53,Dashboard!B12,'Derived Data'!$K$6:$K$53) -> 18080000 | D12: =SUMIF('Derived Data'!$A$6:$N$53,Dashboard!B12,'Derived Data'!$L$6:$L$53) -> 17976125 | E12: =D12-C12 -> -103875 | F12: =SUMIF('Derived Data'!$A$6:$N$534,Dashboard!B12,'Derived Data'!$M$6:$M$53) -> -255000 | G12: =SUMIF('Derived Data'!$A$6:$N$53,Dashboard!B12,'Derived Data'!$N$6:$N$53) -> 151125 | H12: =IFERROR(E12/C12,"n/a") -> -0.0057452987
B13: =EDATE(B12,1) -> 45627 | C13: =SUMIF('Derived Data'!$A$6:$N$53,Dashboard!B13,'Derived Data'!$K$6:$K$53) -> 18415000 | D13: =SUMIF('Derived Data'!$A$6:$N$53,Dashboard!B13,'Derived Data'!$L$6:$L$53) -> 18635275 | E13: =D13-C13 -> 220275 | F13: =SUMIF('Derived Data'!$A$6:$N$534,Dashboard!B13,'Derived Data'!$M$6:$M$53) -> 310000 | G13: =SUMIF('Derived Data'!$A$6:$N$53,Dashboard!B13,'Derived Data'!$N$6:$N$53) -> -89725 | H13: =IFERROR(E13/C13,"n/a") -> 0.011961716
B14: =EDATE(B13,1) -> 45658 | C14: =SUMIF('Derived Data'!$A$6:$N$53,Dashboard!B14,'Derived Data'!$K$6:$K$53) -> 18325000 | D14: =SUMIF('Derived Data'!$A$6:$N$53,Dashboard!B14,'Derived Data'!$L$6:$L$53) -> 18203200 | E14: =D14-C14 -> -121800 | F14: =SUMIF('Derived Data'!$A$6:$N$534,Dashboard!B14,'Derived Data'!$M$6:$M$53) -> -210000 | G14: =SUMIF('Derived Data'!$A$6:$N$53,Dashboard!B14,'Derived Data'!$N$6:$N$53) -> 88200 | H14: =IFERROR(E14/C14,"n/a") -> -0.0066466576
B15: =EDATE(B14,1) -> 45689 | C15: =SUMIF('Derived Data'!$A$6:$N$53,Dashboard!B15,'Derived Data'!$K$6:$K$53) -> 17720000 | D15: =SUMIF('Derived Data'!$A$6:$N$53,Dashboard!B15,'Derived Data'!$L$6:$L$53) -> 17945750 | E15: =D15-C15 -> 225750 | F15: =SUMIF('Derived Data'!$A$6:$N$534,Dashboard!B15,'Derived Data'!$M$6:$M$53) -> 305000 | G15: =SUMIF('Derived Data'!$A$6:$N$53,Dashboard!B15,'Derived Data'!$N$6:$N$53) -> -79250 | H15: =IFERROR(E15/C15,"n/a") -> 0.012739842
B16: =EDATE(B15,1) -> 45717 | C16: =SUMIF('Derived Data'!$A$6:$N$53,Dashboard!B16,'Derived Data'!$K$6:$K$53) -> 16900000 | D16: =SUMIF('Derived Data'!$A$6:$N$53,Dashboard!B16,'Derived Data'!$L$6:$L$53) -> 17236500 | E16: =D16-C16 -> 336500 | F16: =SUMIF('Derived Data'!$A$6:$N$534,Dashboard!B16,'Derived Data'!$M$6:$M$53) -> 635000 | G16: =SUMIF('Derived Data'!$A$6:$N$53,Dashboard!B16,'Derived Data'!$N$6:$N$53) -> -298500 | H16: =IFERROR(E16/C16,"n/a") -> 0.019911243
B20: Revenue Variance By Product
B21: Products | C21: Sum of Budgeted Revenue (Rs) | D21: Sum of Actual Revenue | E21: Sum of Volume Variance | F21: Sum of Price Variance | G21: Revenue Variance | H21: Var%
B22: Green Tea (250g) | C22: =SUMIF('Derived Data'!$B$6:$O$53,Dashboard!B22,'Derived Data'!$K$6:$K$53) -> 42750000 | D22: =SUMIF('Derived Data'!$B$6:$O$53,Dashboard!B22,'Derived Data'!$L$6:$L$53) -> 43023145 | E22: =SUMIF('Derived Data'!$B$6:$O$53,Dashboard!B22,'Derived Data'!$M$6:$M$53) -> 292500 | F22: =SUMIF('Derived Data'!$B$6:$O$53,Dashboard!B22,'Derived Data'!$N$6:$N$53) -> -19355 | G22: =D22-C22 -> 273145 | H22: =G22/C22 -> 0.0063893567
B23: Oats (500g) | C23: =SUMIF('Derived Data'!$B$6:$O$53,Dashboard!B23,'Derived Data'!$K$6:$K$53) -> 47175000 | D23: =SUMIF('Derived Data'!$B$6:$O$53,Dashboard!B23,'Derived Data'!$L$6:$L$53) -> 47296175 | E23: =SUMIF('Derived Data'!$B$6:$O$53,Dashboard!B23,'Derived Data'!$M$6:$M$53) -> 180000 | F23: =SUMIF('Derived Data'!$B$6:$O$53,Dashboard!B23,'Derived Data'!$N$6:$N$53) -> -58825 | G23: =D23-C23 -> 121175 | H23: =G23/C23 -> 0.0025686275
B24: Peanut Butter (400g) | C24: =SUMIF('Derived Data'!$B$6:$O$53,Dashboard!B24,'Derived Data'!$K$6:$K$53) -> 39780000 | D24: =SUMIF('Derived Data'!$B$6:$O$53,Dashboard!B24,'Derived Data'!$L$6:$L$53) -> 40017175 | E24: =SUMIF('Derived Data'!$B$6:$O$53,Dashboard!B24,'Derived Data'!$M$6:$M$53) -> 360000 | F24: =SUMIF('Derived Data'!$B$6:$O$53,Dashboard!B24,'Derived Data'!$N$6:$N$53) -> -122825 | G24: =D24-C24 -> 237175 | H24: =G24/C24 -> 0.0059621669
B25: Olive Oil (1L) | C25: =SUMIF('Derived Data'!$B$6:$O$53,Dashboard!B25,'Derived Data'!$K$6:$K$53) -> 79200000 | D25: =SUMIF('Derived Data'!$B$6:$O$53,Dashboard!B25,'Derived Data'!$L$6:$L$53) -> 79630675 | E25: =SUMIF('Derived Data'!$B$6:$O$53,Dashboard!B25,'Derived Data'!$M$6:$M$53) -> 696000 | F25: =SUMIF('Derived Data'!$B$6:$O$53,Dashboard!B25,'Derived Data'!$N$6:$N$53) -> -265325 | G25: =D25-C25 -> 430675 | H25: =G25/C25 -> 0.0054378157
B26: Grand Total | C26: =SUM(C22:C25) -> 208905000 | D26: =SUM(D22:D25) -> 209967170 | E26: =SUM(E22:E25) -> 1528500 | F26: =SUM(F22:F25) -> -466330 | G26: =SUM(G22:G25) -> 1062170
B29: Total Budget Revenue | C29: Total Actual Revenue | D29: Variance | E29: Variance %
B30: =SUM('Derived Data'!K6:K53)/10000000 -> 20.8905 | C30: =SUM('Derived Data'!L6:L53)/10000000 -> 20.996717 | D30: =C30-B30 -> 0.106217 | E30: =(C30-B30)/B30 -> 0.0050844642
B33: Gross Profit Analysis
B34: Particular | C34: Budget | D34: Actuals | E34: Variance | F34: Variance %
B36: Revenue | C36: =C26 -> 208905000 | D36: =D26 -> 209967170 | E36: =G26 -> 1062170 | F36: =E36/C36 -> 0.0050844642
B37: Cogs | C37: =SUM('Derived Data'!P6:P53) -> 110599000 | D37: =SUM('Derived Data'!Q6:Q53) -> 112059524 | E37: =C37-D37 -> -1460524 | F37: =E37/C37 -> -0.013205581
B38: Gross Profit | C38: =C36-C37 -> 98306000 | D38: =D36-D37 -> 97907646 | E38: =E36-E37 -> 2522694 | F38: =E38/C38 -> 0.025661648
B39: Gross Margin % | C39: =C38/C36 -> 0.47057754 | D39: =D38/D36 -> 0.46629978 | E39: =D39-C39 -> -0.0042777513

Sheet Derived Data
A1: Shyam Consumer Goods Pvt. Ltd.
A2: FMCG Budget vs Actual Data | FY 2024-25
A3: derived data
A4: All figures in Rs.
A5: Month | B5: Product Category | C5: Budget Volume (Units) | D5: Actual Volume (Units) | E5: Budget Price (Rs/Unit) | F5: Actual Price (Rs/Unit) | G5: Budget COGS (Rs/Unit) | H5: Actual COGS (Rs/Unit) | I5: Budget Fixed Overhead (Rs) | J5: Actual Fixed Overhead (Rs) | K5: Budgeted Revenue (Rs) | L5: Actual Revenue | M5: Volume Variance | N5: Price Variance | O5: Total Variance | P5: Budgeted COGS | Q5: Actual COGS | R5: Total Cogs Variance
A6: 45383 | B6: Green Tea (250g) | C6: 15000 | D6: 15420 | E6: 250 | F6: 248.5 | G6: 120 | H6: 121.2 | I6: 200000 | J6: 201500 | K6: =C6*E6 -> 3750000 | L6: =D6*F6 -> 3831870 | M6: =(D6-C6)*E6 -> 105000 | N6: =(F6-E6)*D6 -> -23130 | O6: =M6+N6 -> 81870 | P6: =G6*C6 -> 1800000 | Q6: =H6*D6 -> 1868904 | R6: =Q6-P6 -> 68904
A7: 45383 | B7: Oats (500g) | C7: 25000 | D7: 24100 | E7: 150 | F7: 152 | G7: 70 | H7: 68.5 | I7: 150000 | J7: 149000 | K7: =C7*E7 -> 3750000 | L7: =D7*F7 -> 3663200 | M7: =(D7-C7)*E7 -> -135000 | N7: =(F7-E7)*D7 -> 48200 | O7: =M7+N7 -> -86800 | P7: =G7*C7 -> 1750000 | Q7: =H7*D7 -> 1650850 | R7: =Q7-P7 -> -99150
A8: 45383 | B8: Peanut Butter (400g) | C8: 10000 | D8: 9850 | E8: 300 | F8: 295 | G8: 140 | H8: 142.3 | I8: 180000 | J8: 183200 | K8: =C8*E8 -> 3000000 | L8: =D8*F8 -> 2905750 | M8: =(D8-C8)*E8 -> -45000 | N8: =(F8-E8)*D8 -> -49250 | O8: =M8+N8 -> -94250 | P8: =G8*C8 -> 1400000 | Q8: =H8*D8 -> 1401655 | R8: =Q8-P8 -> 1655
A9: 45383 | B9: Olive Oil (1L) | C9: 8000 | D9: 8120 | E9: 800 | F9: 805 | G9: 500 | H9: 505 | I9: 300000 | J9: 298500 | K9: =C9*E9 -> 6400000 | L9: =D9*F9 -> 6536600 | M9: =(D9-C9)*E9 -> 96000 | N9: =(F9-E9)*D9 -> 40600 | O9: =M9+N9 -> 136600 | P9: =G9*C9 -> 4000000 | Q9: =H9*D9 -> 4100600 | R9: =Q9-P9 -> 100600
A10: 45413 | B10: Green Tea (250g) | C10: 15500 | D10: 15800 | E10: 250 | F10: 250 | G10: 120 | H10: 119.5 | I10: 200000 | J10: 202100 | K10: =C10*E10 -> 3875000 | L10: =D10*F10 -> 3950000 | M10: =(D10-C10)*E10 -> 75000 | N10: =(F10-E10)*D10 -> 0 | O10: =M10+N10 -> 75000 | P10: =G10*C10 -> 1860000 | Q10: =H10*D10 -> 1888100 | R10: =Q10-P10 -> 28100
A11: 45413 | B11: Oats (500g) | C11: 24500 | D11: 24650 | E11: 150 | F11: 148.5 | G11: 70 | H11: 71.1 | I11: 150000 | J11: 152000 | K11: =C11*E11 -> 3675000 | L11: =D11*F11 -> 3660525 | M11: =(D11-C11)*E11 -> 22500 | N11: =(F11-E11)*D11 -> -36975 | O11: =M11+N11 -> -14475 | P11: =G11*C11 -> 1715000 | Q11: =H11*D11 -> 1752615 | R11: =Q11-P11 -> 37615
A12: 45413 | B12: Peanut Butter (400g) | C12: 9800 | D12: 9900 | E12: 300 | F12: 300 | G12: 140 | H12: 139.8 | I12: 180000 | J12: 179500 | K12: =C12*E12 -> 2940000 | L12: =D12*F12 -> 2970000 | M12: =(D12-C12)*E12 -> 30000 | N12: =(F12-E12)*D12 -> 0 | O12: =M12+N12 -> 30000 | P12: =G12*C12 -> 1372000 | Q12: =H12*D12 -> 1384020 | R12: =Q12-P12 -> 12020
A13: 45413 | B13: Olive Oil (1L) | C13: 8100 | D13: 7950 | E13: 800 | F13: 790 | G13: 500 | H13: 495.5 | I13: 300000 | J13: 305000 | K13: =C13*E13 -> 6480000 | L13: =D13*F13 -> 6280500 | M13: =(D13-C13)*E13 -> -120000 | N13: =(F13-E13)*D13 -> -79500 | O13: =M13+N13 -> -199500 | P13: =G13*C13 -> 4050000 | Q13: =H13*D13 -> 3939225 | R13: =Q13-P13 -> -110775
A14: 45444 | B14: Green Tea (250g) | C14: 16000 | D14: 15950 | E14: 250 | F14: 252 | G14: 120 | H14: 122 | I14: 200000 | J14: 199000 | K14: =C14*E14 -> 4000000 | L14: =D14*F14 -> 4019400 | M14: =(D14-C14)*E14 -> -12500 | N14: =(F14-E14)*D14 -> 31900 | O14: =M14+N14 -> 19400 | P14: =G14*C14 -> 1920000 | Q14: =H14*D14 -> 1945900 | R14: =Q14-P14 -> 25900
A15: 45444 | B15: Oats (500g) | C15: 24000 | D15: 23800 | E15: 150 | F15: 151.5 | G15: 70 | H15: 69.9 | I15: 150000 | J15: 150500 | K15: =C15*E15 -> 3600000 | L15: =D15*F15 -> 3605700 | M15: =(D15-C15)*E15 -> -30000 | N15: =(F15-E15)*D15 -> 35700 | O15: =M15+N15 -> 5700 | P15: =G15*C15 -> 1680000 | Q15: =H15*D15 -> 1663620 | R15: =Q15-P15 -> -16380
A16: 45444 | B16: Peanut Butter (400g) | C16: 9500 | D16: 9200 | E16: 300 | F16: 305 | G16: 140 | H16: 143 | I16: 180000 | J16: 181000 | K16: =C16*E16 -> 2850000 | L16: =D16*F16 -> 2806000 | M16: =(D16-C16)*E16 -> -90000 | N16: =(F16-E16)*D16 -> 46000 | O16: =M16+N16 -> -44000 | P16: =G16*C16 -> 1330000 | Q16: =H16*D16 -> 1315600 | R16: =Q16-P16 -> -14400
A17: 45444 | B17: Olive Oil (1L) | C17: 8200 | D17: 8350 | E17: 800 | F17: 798.5 | G17: 500 | H17: 502.2 | I17: 300000 | J17: 299000 | K17: =C17*E17 -> 6560000 | L17: =D17*F17 -> 6667475 | M17: =(D17-C17)*E17 -> 120000 | N17: =(F17-E17)*D17 -> -12525 | O17: =M17+N17 -> 107475 | P17: =G17*C17 -> 4100000 | Q17: =H17*D17 -> 4193370 | R17: =Q17-P17 -> 93370
... A53: 45717 | B53: Olive Oil (1L) | C53: 8000 | D53: 8300 | E53: 800 | F53: 785 | G53: 500 | H53: 508 | I53: 300000 | J53: 310000 | K53: =C53*E53 -> 6400000 | L53: =D53*F53 -> 6515500 | M53: =(D53-C53)*E53 -> 240000 | N53: =(F53-E53)*D53 -> -124500 | O53: =M53+N53 -> 115500 | P53: =G53*C53 -> 4000000 | Q53: =H53*D53 -> 4216400 | R53: =Q53-P53 -> 216400

Sheet Raw Data
A1: Month | B1: Product Category | C1: Budget Volume (Units) | D1: Actual Volume (Units) | E1: Budget Price (Rs/Unit) | F1: Actual Price (Rs/Unit) | G1: Budget COGS (Rs/Unit) | H1: Actual COGS (Rs/Unit) | I1: Budget Fixed Overhead (Rs) | J1: Actual Fixed Overhead (Rs)
A2: 45383 | B2: Green Tea (250g) | C2: 15000 | D2: 15420 | E2: 250 | F2: 248.5 | G2: 120 | H2: 121.2 | I2: 200000 | J2: 201500
A3: 45383 | B3: Oats (500g) | C3: 25000 | D3: 24100 | E3: 150 | F3: 152 | G3: 70 | H3: 68.5 | I3: 150000 | J3: 149000
A4: 45383 | B4: Peanut Butter (400g) | C4: 10000 | D4: 9850 | E4: 300 | F4: 295 | G4: 140 | H4: 142.3 | I4: 180000 | J4: 183200
A5: 45383 | B5: Olive Oil (1L) | C5: 8000 | D5: 8120 | E5: 800 | F5: 805 | G5: 500 | H5: 505 | I5: 300000 | J5: 298500
A6: 45413 | B6: Green Tea (250g) | C6: 15500 | D6: 15800 | E6: 250 | F6: 250 | G6: 120 | H6: 119.5 | I6: 200000 | J6: 202100
A7: 45413 | B7: Oats (500g) | C7: 24500 | D7: 24650 | E7: 150 | F7: 148.5 | G7: 70 | H7: 71.1 | I7: 150000 | J7: 152000
A8: 45413 | B8: Peanut Butter (400g) | C8: 9800 | D8: 9900 | E8: 300 | F8: 300 | G8: 140 | H8: 139.8 | I8: 180000 | J8: 179500
A9: 45413 | B9: Olive Oil (1L) | C9: 8100 | D9: 7950 | E9: 800 | F9: 790 | G9: 500 | H9: 495.5 | I9: 300000 | J9: 305000
A10: 45444 | B10: Green Tea (250g) | C10: 16000 | D10: 15950 | E10: 250 | F10: 252 | G10: 120 | H10: 122 | I10: 200000 | J10: 199000
A11: 45444 | B11: Oats (500g) | C11: 24000 | D11: 23800 | E11: 150 | F11: 151.5 | G11: 70 | H11: 69.9 | I11: 150000 | J11: 150500
A12: 45444 | B12: Peanut Butter (400g) | C12: 9500 | D12: 9200 | E12: 300 | F12: 305 | G12: 140 | H12: 143 | I12: 180000 | J12: 181000
A13: 45444 | B13: Olive Oil (1L) | C13: 8200 | D13: 8350 | E13: 800 | F13: 798.5 | G13: 500 | H13: 502.2 | I13: 300000 | J13: 299000
... A49: 45717 | B49: Olive Oil (1L) | C49: 8000 | D49: 8300 | E49: 800 | F49: 785 | G49: 500 | H49: 508 | I49: 300000 | J49: 310000
